pystyile/__init__.py
pystyile-3.0.dist-info/METADATA
pystyile-3.0.dist-info/WHEEL
pystyile-3.0.dist-info/top_level.txt
pystyile-3.0.dist-info/RECORD
